{
  "dataset": "enterprise",
  "count_unit": "entity",
  "entity_key": "11340111002992154J",
  "selection_source": "local_exact_match",
  "normalized_projection": {
    "unified_social_credit_code": "11340111002992154J",
    "enterprise_name": "合肥市包河区住房和城乡建设局",
    "legal_representative": "未公示",
    "entity_type": "-",
    "established_date": "1/1/1970 00:00:00",
    "registration_authority": "",
    "registered_capital": "0",
    "business_status": "开业",
    "registered_address": "合肥市包河大道118号",
    "business_scope": "未公示",
    "source_url": "",
    "administrative_licenses": [],
    "administrative_penalties": [],
    "annual_reports": [],
    "spot_checks": [],
    "abnormal_operations": [],
    "serious_illegal_list": []
  },
  "tender_linkage": {
    "selected_project_frequency": 12,
    "all_tender_frequency": 263,
    "selected_project_ids": [
      "2023ABBFN00205",
      "2023ABBFN00216",
      "2023ABBFN00217",
      "2023ABBFN00218",
      "2023ABBFN00219",
      "2023ABBFZ00208",
      "2023ABBFZ00209",
      "2023ABBFZ00210",
      "2023ABBFZ00211",
      "2023ABBFZ00213",
      "2023ABBFZ00214",
      "2023BBBBZ00099"
    ],
    "all_linked_project_ids": [
      "2022ABBFN00218",
      "2022ABBFN00220",
      "2022ABBFN00223",
      "2022ABBFN00237",
      "2022ABBHN00235",
      "2023ABBFN00205",
      "2023ABBFN00216",
      "2023ABBFN00217",
      "2023ABBFN00218",
      "2023ABBFN00219",
      "2023ABBFZ00208",
      "2023ABBFZ00209",
      "2023ABBFZ00210",
      "2023ABBFZ00211",
      "2023ABBFZ00213",
      "2023ABBFZ00214",
      "2023ABBZJ00170",
      "2023ABBZJ00201",
      "2023BBBBZ00099"
    ],
    "roles": [
      "purchaser"
    ]
  },
  "raw_profile": {
    "company_name": "合肥市包河区住房和城乡建设局",
    "business_status": "开业",
    "legal_representative": "未公示",
    "registered_capital": "0",
    "paid_in_capital": "0",
    "establishment_date": "1/1/1970 00:00:00",
    "approval_date": "1/1/1970 00:00:00",
    "business_term": "-",
    "province": "安徽省",
    "city": "合肥市",
    "district": "包河区",
    "phone": "0551-66223831",
    "additional_phones": "0551-6335783,13966712597,0551-63357649,0551-63357279,0551-63357280",
    "email": "-",
    "additional_emails": "-",
    "unified_social_credit_code": "11340111002992154J",
    "taxpayer_identification_number": "11340111002992154J",
    "business_registration_number": "-",
    "organization_code": "00299215-4",
    "insured_personnel_count": "-",
    "company_type": "-",
    "industry": "-",
    "former_name": "-",
    "registered_address": "合肥市包河大道118号",
    "latest_annual_report_address": "-",
    "website": "-",
    "business_scope": "未公示",
    "match_status": "成功"
  }
}