{
  "dataset": "enterprise",
  "count_unit": "entity",
  "entity_key": "113401210030046722",
  "selection_source": "local_exact_match",
  "normalized_projection": {
    "unified_social_credit_code": "113401210030046722",
    "enterprise_name": "长丰县左店镇人民政府",
    "legal_representative": "未公示",
    "entity_type": "-",
    "established_date": "1/1/1970 00:00:00",
    "registration_authority": "",
    "registered_capital": "0",
    "business_status": "开业",
    "registered_address": "长丰县左店镇街道",
    "business_scope": "未公示",
    "source_url": "",
    "administrative_licenses": [],
    "administrative_penalties": [],
    "annual_reports": [],
    "spot_checks": [],
    "abnormal_operations": [],
    "serious_illegal_list": []
  },
  "tender_linkage": {
    "selected_project_frequency": 2,
    "all_tender_frequency": 36,
    "selected_project_ids": [
      "2023ACCFZ00492",
      "2023ACCZN00510"
    ],
    "all_linked_project_ids": [
      "2023ACCFN00009",
      "2023ACCFZ00492",
      "2023ACCHZ00404",
      "2023ACCHZ00443",
      "2023ACCZN00026",
      "2023ACCZN00029",
      "2023ACCZN00086",
      "2023ACCZN00307",
      "2023ACCZN00510"
    ],
    "roles": [
      "purchaser"
    ]
  },
  "raw_profile": {
    "company_name": "长丰县左店镇人民政府",
    "business_status": "开业",
    "legal_representative": "未公示",
    "registered_capital": "0",
    "paid_in_capital": "0",
    "establishment_date": "1/1/1970 00:00:00",
    "approval_date": "1/1/1970 00:00:00",
    "business_term": "-",
    "province": "安徽省",
    "city": "合肥市",
    "district": "长丰县",
    "phone": "13966734587",
    "additional_phones": "13359065399,18225832424,18556533841,18356026790,0551-69016629",
    "email": "-",
    "additional_emails": "-",
    "unified_social_credit_code": "113401210030046722",
    "taxpayer_identification_number": "113401210030046722",
    "business_registration_number": "-",
    "organization_code": "00300467-2",
    "insured_personnel_count": "-",
    "company_type": "-",
    "industry": "-",
    "former_name": "-",
    "registered_address": "长丰县左店镇街道",
    "latest_annual_report_address": "-",
    "website": "-",
    "business_scope": "未公示",
    "match_status": "成功"
  }
}