{
  "dataset": "enterprise",
  "count_unit": "entity",
  "entity_key": "91340100689782961L",
  "selection_source": "local_exact_match",
  "normalized_projection": {
    "unified_social_credit_code": "91340100689782961L",
    "enterprise_name": "合肥市轨道交通集团有限公司",
    "legal_representative": "何轶鸥",
    "entity_type": "有限责任公司(国有独资)",
    "established_date": "2/6/2009 00:00:00",
    "registration_authority": "",
    "registered_capital": "5359000000",
    "business_status": "开业",
    "registered_address": "安徽省合肥市阜阳路17号",
    "business_scope": "许可项目：城市公共交通；建设工程施工（除核电站建设经营、民用机场建设）；房地产开发经营（依法须经批准的项目，经相关部门批准后方可开展经营活动，具体经营项目以相关部门批准文件或许可证件为准）一般项目：以自有资金从事投资活动；规划设计管理；工程造价咨询业务；工程管理服务；商业综合体管理服务；土地整治服务；土地使用权租赁；房地产咨询；轨道交通专用设备、关键系统及部件销售；非居住房地产租赁；住房租赁；广告制作；广告发布；广告设计、代理；物业管理；酒店管理；业务培训（不含教育培训、职业技能培训等需取得许可的培训）；安全咨询服务；教育咨询服务（不含涉许可审批的教育培训活动）；企业管理咨询（除许可业务外，可自主依法经营法律法规非禁止或限制的项目）",
    "source_url": "",
    "administrative_licenses": [],
    "administrative_penalties": [],
    "annual_reports": [],
    "spot_checks": [],
    "abnormal_operations": [],
    "serious_illegal_list": []
  },
  "tender_linkage": {
    "selected_project_frequency": 7,
    "all_tender_frequency": 447,
    "selected_project_ids": [
      "2023BFFAZ02454",
      "2023BFFAZ02468",
      "2023BFFBZ02536",
      "2023BFFBZ02613",
      "2023BFFGZ02614",
      "2023BFFGZ02685",
      "2023BFFWZ02402"
    ],
    "all_linked_project_ids": [
      "2023BFFAZ01978",
      "2023BFFAZ02073",
      "2023BFFAZ02083",
      "2023BFFAZ02132",
      "2023BFFAZ02175",
      "2023BFFAZ02251",
      "2023BFFAZ02454",
      "2023BFFAZ02468",
      "2023BFFBZ02218",
      "2023BFFBZ02222",
      "2023BFFBZ02223",
      "2023BFFBZ02286",
      "2023BFFBZ02358",
      "2023BFFBZ02536",
      "2023BFFBZ02613",
      "2023BFFGZ02363",
      "2023BFFGZ02394",
      "2023BFFGZ02614",
      "2023BFFGZ02685",
      "2023BFFWZ02402",
      "2023JFABZ02032"
    ],
    "roles": [
      "purchaser"
    ]
  },
  "raw_profile": {
    "company_name": "合肥市轨道交通集团有限公司",
    "business_status": "开业",
    "legal_representative": "何轶鸥",
    "registered_capital": "5359000000",
    "paid_in_capital": "5359000000",
    "establishment_date": "2/6/2009 00:00:00",
    "approval_date": "28/7/2022 00:00:00",
    "business_term": "-",
    "province": "安徽省",
    "city": "合肥市",
    "district": "庐阳区",
    "phone": "0551-62665235",
    "additional_phones": "0551-62079090,0551-62662726,18801303274,0551-62662805,0551-69009055",
    "email": "1432392593@qq.com",
    "additional_emails": "463930728@qq.com,304217781@qq.com,357371638@qq.com",
    "unified_social_credit_code": "91340100689782961L",
    "taxpayer_identification_number": "91340100689782961L",
    "business_registration_number": "340100000295935",
    "organization_code": "68978296-1",
    "insured_personnel_count": "667",
    "company_type": "有限责任公司(国有独资)",
    "industry": "道路运输业",
    "former_name": "-",
    "registered_address": "安徽省合肥市阜阳路17号",
    "latest_annual_report_address": "合肥市庐阳区阜阳路17号",
    "website": "www.hfgdjt.com",
    "business_scope": "许可项目：城市公共交通；建设工程施工（除核电站建设经营、民用机场建设）；房地产开发经营（依法须经批准的项目，经相关部门批准后方可开展经营活动，具体经营项目以相关部门批准文件或许可证件为准）一般项目：以自有资金从事投资活动；规划设计管理；工程造价咨询业务；工程管理服务；商业综合体管理服务；土地整治服务；土地使用权租赁；房地产咨询；轨道交通专用设备、关键系统及部件销售；非居住房地产租赁；住房租赁；广告制作；广告发布；广告设计、代理；物业管理；酒店管理；业务培训（不含教育培训、职业技能培训等需取得许可的培训）；安全咨询服务；教育咨询服务（不含涉许可审批的教育培训活动）；企业管理咨询（除许可业务外，可自主依法经营法律法规非禁止或限制的项目）",
    "match_status": "成功"
  }
}