{
  "request": {
    "SOURCE_TYPE": "1",
    "DEAL_TIME": "06",
    "TIMEBEGIN": "2023-11-01",
    "TIMEEND": "2024-03-28",
    "DEAL_PROVINCE": "340000",
    "DEAL_CITY": "340100",
    "PAGENUMBER": "8"
  },
  "response": {
    "code": 200,
    "message": "success",
    "data": {
      "records": [
        {
          "id": "0034e4323400f63d4d66a1ecc48ec162975d",
          "addTime": null,
          "publishTime": "2024-03-28",
          "deadline": null,
          "dataSources": null,
          "dataSourcesText": null,
          "transactionSourcesPlatform": null,
          "transactionSourcesPlatformText": null,
          "businessType": null,
          "businessTypeText": "工程建设",
          "informationType": "0104",
          "informationTypeText": "交易结果公示",
          "industryType": null,
          "industryTypeText": null,
          "province": "340000",
          "provinceText": "安徽省",
          "city": null,
          "cityText": null,
          "title": "中国银行总行金融科技中心合肥园区项目电梯设备采购及安装中标候选人公示",
          "tenderProjectCode": null,
          "bodyContent": null,
          "url": "/his/information/deal/html/a/340000/0104/20240328/0034e4323400f63d4d66a1ecc48ec162975d.html",
          "syncTableName": null,
          "dataTimestamp": null,
          "pinformationType": null
        },
        {
          "id": "0034e4323400f63d4d66a1ecc48ec162975d",
          "addTime": null,
          "publishTime": "2024-03-28",
          "deadline": null,
          "dataSources": null,
          "dataSourcesText": null,
          "transactionSourcesPlatform": null,
          "transactionSourcesPlatformText": null,
          "businessType": null,
          "businessTypeText": "工程建设",
          "informationType": "0104",
          "informationTypeText": "交易结果公示",
          "industryType": null,
          "industryTypeText": null,
          "province": "340000",
          "provinceText": "安徽省",
          "city": null,
          "cityText": null,
          "title": "中国银行总行金融科技中心合肥园区项目电梯设备采购及安装中标候选人公示",
          "tenderProjectCode": null,
          "bodyContent": null,
          "url": "/his/information/deal/html/a/340000/0104/20240328/0034e4323400f63d4d66a1ecc48ec162975d.html",
          "syncTableName": null,
          "dataTimestamp": null,
          "pinformationType": null
        },
        {
          "id": "0034ccf4bfc6f270414a85d3c35b1ac31da9",
          "addTime": null,
          "publishTime": "2024-03-28",
          "deadline": null,
          "dataSources": null,
          "dataSourcesText": null,
          "transactionSourcesPlatform": null,
          "transactionSourcesPlatformText": null,
          "businessType": null,
          "businessTypeText": "政府采购",
          "informationType": "0202",
          "informationTypeText": "中标公告",
          "industryType": null,
          "industryTypeText": "",
          "province": "340000",
          "provinceText": "安徽省",
          "city": null,
          "cityText": null,
          "title": "2024年合肥市教育系统网络安全监测管理服务项目中标（成交）结果公告",
          "tenderProjectCode": null,
          "bodyContent": null,
          "url": "/his/information/deal/html/a/340000/0202/20240328/0034ccf4bfc6f270414a85d3c35b1ac31da9.html",
          "syncTableName": null,
          "dataTimestamp": null,
          "pinformationType": null
        },
        {
          "id": "0034ccf4bfc6f270414a85d3c35b1ac31da9",
          "addTime": null,
          "publishTime": "2024-03-28",
          "deadline": null,
          "dataSources": null,
          "dataSourcesText": null,
          "transactionSourcesPlatform": null,
          "transactionSourcesPlatformText": null,
          "businessType": null,
          "businessTypeText": "政府采购",
          "informationType": "0202",
          "informationTypeText": "中标公告",
          "industryType": null,
          "industryTypeText": "",
          "province": "340000",
          "provinceText": "安徽省",
          "city": null,
          "cityText": null,
          "title": "2024年合肥市教育系统网络安全监测管理服务项目中标（成交）结果公告",
          "tenderProjectCode": null,
          "bodyContent": null,
          "url": "/his/information/deal/html/a/340000/0202/20240328/0034ccf4bfc6f270414a85d3c35b1ac31da9.html",
          "syncTableName": null,
          "dataTimestamp": null,
          "pinformationType": null
        },
        {
          "id": "0034c8f0da5749694ee68190b06bd3ee8da7",
          "addTime": null,
          "publishTime": "2024-03-28",
          "deadline": null,
          "dataSources": null,
          "dataSourcesText": null,
          "transactionSourcesPlatform": null,
          "transactionSourcesPlatformText": "安徽合肥公共资源交易中心电子交易系统",
          "businessType": null,
          "businessTypeText": "工程建设",
          "informationType": "0104",
          "informationTypeText": "交易结果公示",
          "industryType": null,
          "industryTypeText": null,
          "province": "340000",
          "provinceText": "安徽省",
          "city": null,
          "cityText": null,
          "title": "杨庙镇马郢村和美乡村精品示范村第一批建设项目中标候选人公示",
          "tenderProjectCode": null,
          "bodyContent": null,
          "url": "/his/information/deal/html/a/340000/0104/20240328/0034c8f0da5749694ee68190b06bd3ee8da7.html",
          "syncTableName": null,
          "dataTimestamp": null,
          "pinformationType": null
        },
        {
          "id": "0034c8f0da5749694ee68190b06bd3ee8da7",
          "addTime": null,
          "publishTime": "2024-03-28",
          "deadline": null,
          "dataSources": null,
          "dataSourcesText": null,
          "transactionSourcesPlatform": null,
          "transactionSourcesPlatformText": "安徽合肥公共资源交易中心电子交易系统",
          "businessType": null,
          "businessTypeText": "工程建设",
          "informationType": "0104",
          "informationTypeText": "交易结果公示",
          "industryType": null,
          "industryTypeText": null,
          "province": "340000",
          "provinceText": "安徽省",
          "city": null,
          "cityText": null,
          "title": "杨庙镇马郢村和美乡村精品示范村第一批建设项目中标候选人公示",
          "tenderProjectCode": null,
          "bodyContent": null,
          "url": "/his/information/deal/html/a/340000/0104/20240328/0034c8f0da5749694ee68190b06bd3ee8da7.html",
          "syncTableName": null,
          "dataTimestamp": null,
          "pinformationType": null
        },
        {
          "id": "0034c0ea4f5fef4848fb8678912f66f977c2",
          "addTime": null,
          "publishTime": "2024-03-28",
          "deadline": null,
          "dataSources": null,
          "dataSourcesText": null,
          "transactionSourcesPlatform": null,
          "transactionSourcesPlatformText": null,
          "businessType": null,
          "businessTypeText": "国有产权",
          "informationType": "0501",
          "informationTypeText": "挂牌披露",
          "industryType": null,
          "industryTypeText": "",
          "province": "340000",
          "provinceText": "安徽省",
          "city": null,
          "cityText": null,
          "title": "安徽泓瑞嘉珑酒店宿舍楼二层14间宿舍租赁",
          "tenderProjectCode": null,
          "bodyContent": null,
          "url": "/his/information/deal/html/a/340000/0501/20240328/0034c0ea4f5fef4848fb8678912f66f977c2.html",
          "syncTableName": null,
          "dataTimestamp": null,
          "pinformationType": null
        },
        {
          "id": "0034c0ea4f5fef4848fb8678912f66f977c2",
          "addTime": null,
          "publishTime": "2024-03-28",
          "deadline": null,
          "dataSources": null,
          "dataSourcesText": null,
          "transactionSourcesPlatform": null,
          "transactionSourcesPlatformText": null,
          "businessType": null,
          "businessTypeText": "国有产权",
          "informationType": "0501",
          "informationTypeText": "挂牌披露",
          "industryType": null,
          "industryTypeText": "",
          "province": "340000",
          "provinceText": "安徽省",
          "city": null,
          "cityText": null,
          "title": "安徽泓瑞嘉珑酒店宿舍楼二层14间宿舍租赁",
          "tenderProjectCode": null,
          "bodyContent": null,
          "url": "/his/information/deal/html/a/340000/0501/20240328/0034c0ea4f5fef4848fb8678912f66f977c2.html",
          "syncTableName": null,
          "dataTimestamp": null,
          "pinformationType": null
        },
        {
          "id": "0034b9d376ce0a7f44918a5c8df027cc0c7d",
          "addTime": null,
          "publishTime": "2024-03-28",
          "deadline": null,
          "dataSources": null,
          "dataSourcesText": null,
          "transactionSourcesPlatform": null,
          "transactionSourcesPlatformText": "安徽合肥公共资源交易中心电子交易系统",
          "businessType": null,
          "businessTypeText": "政府采购",
          "informationType": "0202",
          "informationTypeText": "中标公告",
          "industryType": null,
          "industryTypeText": "",
          "province": "340000",
          "provinceText": "安徽省",
          "city": null,
          "cityText": null,
          "title": "2024年瑶海区道路交通违法车辆拖移、停放保管及应急保障车辆等服务（第1次）中标（成交）结果公告",
          "tenderProjectCode": null,
          "bodyContent": null,
          "url": "/his/information/deal/html/a/340000/0202/20240328/0034b9d376ce0a7f44918a5c8df027cc0c7d.html",
          "syncTableName": null,
          "dataTimestamp": null,
          "pinformationType": null
        },
        {
          "id": "0034b9d376ce0a7f44918a5c8df027cc0c7d",
          "addTime": null,
          "publishTime": "2024-03-28",
          "deadline": null,
          "dataSources": null,
          "dataSourcesText": null,
          "transactionSourcesPlatform": null,
          "transactionSourcesPlatformText": "安徽合肥公共资源交易中心电子交易系统",
          "businessType": null,
          "businessTypeText": "政府采购",
          "informationType": "0202",
          "informationTypeText": "中标公告",
          "industryType": null,
          "industryTypeText": "",
          "province": "340000",
          "provinceText": "安徽省",
          "city": null,
          "cityText": null,
          "title": "2024年瑶海区道路交通违法车辆拖移、停放保管及应急保障车辆等服务（第1次）中标（成交）结果公告",
          "tenderProjectCode": null,
          "bodyContent": null,
          "url": "/his/information/deal/html/a/340000/0202/20240328/0034b9d376ce0a7f44918a5c8df027cc0c7d.html",
          "syncTableName": null,
          "dataTimestamp": null,
          "pinformationType": null
        },
        {
          "id": "0034b68da71273224dc1955ff9b87a0107d7",
          "addTime": null,
          "publishTime": "2024-03-28",
          "deadline": null,
          "dataSources": null,
          "dataSourcesText": null,
          "transactionSourcesPlatform": null,
          "transactionSourcesPlatformText": null,
          "businessType": null,
          "businessTypeText": "工程建设",
          "informationType": "0104",
          "informationTypeText": "交易结果公示",
          "industryType": null,
          "industryTypeText": null,
          "province": "340000",
          "provinceText": "安徽省",
          "city": null,
          "cityText": null,
          "title": "合肥市轨道交通安保控制中心技术大楼及市政预留工程、线网控制及应急救援指挥中心项目、BK202304号宗地项目工程测量及第三方监测项目中标候选人公示",
          "tenderProjectCode": null,
          "bodyContent": null,
          "url": "/his/information/deal/html/a/340000/0104/20240328/0034b68da71273224dc1955ff9b87a0107d7.html",
          "syncTableName": null,
          "dataTimestamp": null,
          "pinformationType": null
        },
        {
          "id": "0034b68da71273224dc1955ff9b87a0107d7",
          "addTime": null,
          "publishTime": "2024-03-28",
          "deadline": null,
          "dataSources": null,
          "dataSourcesText": null,
          "transactionSourcesPlatform": null,
          "transactionSourcesPlatformText": null,
          "businessType": null,
          "businessTypeText": "工程建设",
          "informationType": "0104",
          "informationTypeText": "交易结果公示",
          "industryType": null,
          "industryTypeText": null,
          "province": "340000",
          "provinceText": "安徽省",
          "city": null,
          "cityText": null,
          "title": "合肥市轨道交通安保控制中心技术大楼及市政预留工程、线网控制及应急救援指挥中心项目、BK202304号宗地项目工程测量及第三方监测项目中标候选人公示",
          "tenderProjectCode": null,
          "bodyContent": null,
          "url": "/his/information/deal/html/a/340000/0104/20240328/0034b68da71273224dc1955ff9b87a0107d7.html",
          "syncTableName": null,
          "dataTimestamp": null,
          "pinformationType": null
        },
        {
          "id": "0034b25d15d997fd4a6e8067a13f5f6c6db2",
          "addTime": null,
          "publishTime": "2024-03-28",
          "deadline": null,
          "dataSources": null,
          "dataSourcesText": null,
          "transactionSourcesPlatform": null,
          "transactionSourcesPlatformText": null,
          "businessType": null,
          "businessTypeText": "工程建设",
          "informationType": "0104",
          "informationTypeText": "交易结果公示",
          "industryType": null,
          "industryTypeText": null,
          "province": "340000",
          "provinceText": "安徽省",
          "city": null,
          "cityText": null,
          "title": "合肥市重点局2024年度市政路桥项目电源报装项目中标结果公示",
          "tenderProjectCode": null,
          "bodyContent": null,
          "url": "/his/information/deal/html/a/340000/0104/20240328/0034b25d15d997fd4a6e8067a13f5f6c6db2.html",
          "syncTableName": null,
          "dataTimestamp": null,
          "pinformationType": null
        },
        {
          "id": "0034b25d15d997fd4a6e8067a13f5f6c6db2",
          "addTime": null,
          "publishTime": "2024-03-28",
          "deadline": null,
          "dataSources": null,
          "dataSourcesText": null,
          "transactionSourcesPlatform": null,
          "transactionSourcesPlatformText": null,
          "businessType": null,
          "businessTypeText": "工程建设",
          "informationType": "0104",
          "informationTypeText": "交易结果公示",
          "industryType": null,
          "industryTypeText": null,
          "province": "340000",
          "provinceText": "安徽省",
          "city": null,
          "cityText": null,
          "title": "合肥市重点局2024年度市政路桥项目电源报装项目中标结果公示",
          "tenderProjectCode": null,
          "bodyContent": null,
          "url": "/his/information/deal/html/a/340000/0104/20240328/0034b25d15d997fd4a6e8067a13f5f6c6db2.html",
          "syncTableName": null,
          "dataTimestamp": null,
          "pinformationType": null
        },
        {
          "id": "0034aad98edc8ee347f0b16c9b3a8fdd4505",
          "addTime": null,
          "publishTime": "2024-03-28",
          "deadline": null,
          "dataSources": null,
          "dataSourcesText": null,
          "transactionSourcesPlatform": null,
          "transactionSourcesPlatformText": "安徽合肥公共资源交易中心电子交易系统",
          "businessType": null,
          "businessTypeText": "政府采购",
          "informationType": "0202",
          "informationTypeText": "中标公告",
          "industryType": null,
          "industryTypeText": "",
          "province": "340000",
          "provinceText": "安徽省",
          "city": null,
          "cityText": null,
          "title": "蜀山经济技术开发区建筑工程特种设备检测服务成交结果公告",
          "tenderProjectCode": null,
          "bodyContent": null,
          "url": "/his/information/deal/html/a/340000/0202/20240328/0034aad98edc8ee347f0b16c9b3a8fdd4505.html",
          "syncTableName": null,
          "dataTimestamp": null,
          "pinformationType": null
        },
        {
          "id": "0034aad98edc8ee347f0b16c9b3a8fdd4505",
          "addTime": null,
          "publishTime": "2024-03-28",
          "deadline": null,
          "dataSources": null,
          "dataSourcesText": null,
          "transactionSourcesPlatform": null,
          "transactionSourcesPlatformText": "安徽合肥公共资源交易中心电子交易系统",
          "businessType": null,
          "businessTypeText": "政府采购",
          "informationType": "0202",
          "informationTypeText": "中标公告",
          "industryType": null,
          "industryTypeText": "",
          "province": "340000",
          "provinceText": "安徽省",
          "city": null,
          "cityText": null,
          "title": "蜀山经济技术开发区建筑工程特种设备检测服务成交结果公告",
          "tenderProjectCode": null,
          "bodyContent": null,
          "url": "/his/information/deal/html/a/340000/0202/20240328/0034aad98edc8ee347f0b16c9b3a8fdd4505.html",
          "syncTableName": null,
          "dataTimestamp": null,
          "pinformationType": null
        },
        {
          "id": "0034aacf3da49f2d4c54846d53689ac214d5",
          "addTime": null,
          "publishTime": "2024-03-28",
          "deadline": null,
          "dataSources": null,
          "dataSourcesText": null,
          "transactionSourcesPlatform": null,
          "transactionSourcesPlatformText": "安徽合肥公共资源交易中心电子交易系统",
          "businessType": null,
          "businessTypeText": "国有产权",
          "informationType": "0502",
          "informationTypeText": "交易结果",
          "industryType": null,
          "industryTypeText": "",
          "province": "340000",
          "provinceText": "安徽省",
          "city": null,
          "cityText": null,
          "title": "庐阳工业区杏花分园6号厂房租赁",
          "tenderProjectCode": null,
          "bodyContent": null,
          "url": "/his/information/deal/html/a/340000/0502/20240328/0034aacf3da49f2d4c54846d53689ac214d5.html",
          "syncTableName": null,
          "dataTimestamp": null,
          "pinformationType": null
        },
        {
          "id": "0034aacf3da49f2d4c54846d53689ac214d5",
          "addTime": null,
          "publishTime": "2024-03-28",
          "deadline": null,
          "dataSources": null,
          "dataSourcesText": null,
          "transactionSourcesPlatform": null,
          "transactionSourcesPlatformText": "安徽合肥公共资源交易中心电子交易系统",
          "businessType": null,
          "businessTypeText": "国有产权",
          "informationType": "0502",
          "informationTypeText": "交易结果",
          "industryType": null,
          "industryTypeText": "",
          "province": "340000",
          "provinceText": "安徽省",
          "city": null,
          "cityText": null,
          "title": "庐阳工业区杏花分园6号厂房租赁",
          "tenderProjectCode": null,
          "bodyContent": null,
          "url": "/his/information/deal/html/a/340000/0502/20240328/0034aacf3da49f2d4c54846d53689ac214d5.html",
          "syncTableName": null,
          "dataTimestamp": null,
          "pinformationType": null
        },
        {
          "id": "0034a6aeace18ee441e583ddcd1c987ce05a",
          "addTime": null,
          "publishTime": "2024-03-28",
          "deadline": null,
          "dataSources": null,
          "dataSourcesText": null,
          "transactionSourcesPlatform": null,
          "transactionSourcesPlatformText": "安徽合肥公共资源交易中心电子交易系统",
          "businessType": null,
          "businessTypeText": "工程建设",
          "informationType": "0104",
          "informationTypeText": "交易结果公示",
          "industryType": null,
          "industryTypeText": null,
          "province": "340000",
          "provinceText": "安徽省",
          "city": null,
          "cityText": null,
          "title": "巢湖市烔炀镇凤凰村2024年较大自然村整治提升工程中标候选人公示",
          "tenderProjectCode": null,
          "bodyContent": null,
          "url": "/his/information/deal/html/a/340000/0104/20240328/0034a6aeace18ee441e583ddcd1c987ce05a.html",
          "syncTableName": null,
          "dataTimestamp": null,
          "pinformationType": null
        },
        {
          "id": "0034a6aeace18ee441e583ddcd1c987ce05a",
          "addTime": null,
          "publishTime": "2024-03-28",
          "deadline": null,
          "dataSources": null,
          "dataSourcesText": null,
          "transactionSourcesPlatform": null,
          "transactionSourcesPlatformText": "安徽合肥公共资源交易中心电子交易系统",
          "businessType": null,
          "businessTypeText": "工程建设",
          "informationType": "0104",
          "informationTypeText": "交易结果公示",
          "industryType": null,
          "industryTypeText": null,
          "province": "340000",
          "provinceText": "安徽省",
          "city": null,
          "cityText": null,
          "title": "巢湖市烔炀镇凤凰村2024年较大自然村整治提升工程中标候选人公示",
          "tenderProjectCode": null,
          "bodyContent": null,
          "url": "/his/information/deal/html/a/340000/0104/20240328/0034a6aeace18ee441e583ddcd1c987ce05a.html",
          "syncTableName": null,
          "dataTimestamp": null,
          "pinformationType": null
        }
      ],
      "total": 14726,
      "size": 20,
      "current": 8,
      "orders": [],
      "optimizeCountSql": true,
      "searchCount": true,
      "countId": null,
      "maxLimit": null,
      "pages": 737
    },
    "usetime": 988,
    "timestamp": 1776308908153
  }
}